[{"cem_alpha": 0.08038537420389294, "cem_elites_ratio": 0.16671815566309886, "cem_popsize": 383, "num_cem_iters": 4, "plan_hor": 30}, {"cem_alpha": 0.1153007616245542, "cem_elites_ratio": 0.23312147354440263, "cem_popsize": 385, "num_cem_iters": 5, "plan_hor": 17}, {"cem_alpha": 0.13407761956154163, "cem_elites_ratio": 0.18030992517381805, "cem_popsize": 328, "num_cem_iters": 4, "plan_hor": 39}, {"cem_alpha": 0.1259026755177744, "cem_elites_ratio": 0.14399881020182148, "cem_popsize": 320, "num_cem_iters": 5, "plan_hor": 44}, {"cem_alpha": 0.12621088962676902, "cem_elites_ratio": 0.2634595597237843, "cem_popsize": 347, "num_cem_iters": 5, "plan_hor": 40}, {"cem_alpha": 0.13099142238020928, "cem_elites_ratio": 0.24926531857179793, "cem_popsize": 359, "num_cem_iters": 4, "plan_hor": 33}, {"cem_alpha": 0.12170521274674898, "cem_elites_ratio": 0.1871933804765029, "cem_popsize": 362, "num_cem_iters": 5, "plan_hor": 29}, {"cem_alpha": 0.09654940611952376, "cem_elites_ratio": 0.23830386503450218, "cem_popsize": 367, "num_cem_iters": 6, "plan_hor": 18}, {"cem_alpha": 0.10188187546294167, "cem_elites_ratio": 0.17418915645166208, "cem_popsize": 366, "num_cem_iters": 5, "plan_hor": 30}, {"cem_alpha": 0.1293330720658534, "cem_elites_ratio": 0.2471159629284877, "cem_popsize": 385, "num_cem_iters": 5, "plan_hor": 38}, {"cem_alpha": 0.08847531818024519, "cem_elites_ratio": 0.14613216841165882, "cem_popsize": 374, "num_cem_iters": 5, "plan_hor": 32}, {"cem_alpha": 0.1561775716219931, "cem_elites_ratio": 0.08143640590278835, "cem_popsize": 360, "num_cem_iters": 6, "plan_hor": 13}, {"cem_alpha": 0.13651298664249822, "cem_elites_ratio": 0.0967210253368149, "cem_popsize": 312, "num_cem_iters": 5, "plan_hor": 36}, {"cem_alpha": 0.12132568502928645, "cem_elites_ratio": 0.10666152284724947, "cem_popsize": 353, "num_cem_iters": 4, "plan_hor": 41}, {"cem_alpha": 0.14974651790039295, "cem_elites_ratio": 0.0897435759470042, "cem_popsize": 367, "num_cem_iters": 5, "plan_hor": 40}, {"cem_alpha": 0.12815313765048925, "cem_elites_ratio": 0.13857139873494634, "cem_popsize": 393, "num_cem_iters": 4, "plan_hor": 36}, {"cem_alpha": 0.1294010988756687, "cem_elites_ratio": 0.14104707291885474, "cem_popsize": 318, "num_cem_iters": 7, "plan_hor": 39}, {"cem_alpha": 0.14741336787311965, "cem_elites_ratio": 0.19299657846235196, "cem_popsize": 387, "num_cem_iters": 6, "plan_hor": 18}, {"cem_alpha": 0.11738438812523733, "cem_elites_ratio": 0.16974642076457452, "cem_popsize": 388, "num_cem_iters": 5, "plan_hor": 24}, {"cem_alpha": 0.10822659002314375, "cem_elites_ratio": 0.19643874087775187, "cem_popsize": 397, "num_cem_iters": 6, "plan_hor": 22}, {"cem_alpha": 0.11391607344575601, "cem_elites_ratio": 0.1436985815001656, "cem_popsize": 352, "num_cem_iters": 6, "plan_hor": 35}, {"cem_alpha": 0.11222265174833126, "cem_elites_ratio": 0.09853205624821931, "cem_popsize": 318, "num_cem_iters": 6, "plan_hor": 28}, {"cem_alpha": 0.12095212964894678, "cem_elites_ratio": 0.10580623175946136, "cem_popsize": 308, "num_cem_iters": 4, "plan_hor": 32}, {"cem_alpha": 0.12004478447603528, "cem_elites_ratio": 0.2768865671048273, "cem_popsize": 446, "num_cem_iters": 5, "plan_hor": 35}, {"cem_alpha": 0.12534163428263195, "cem_elites_ratio": 0.17171662061923806, "cem_popsize": 445, "num_cem_iters": 5, "plan_hor": 22}, {"cem_alpha": 0.13505490495742872, "cem_elites_ratio": 0.1920278154625618, "cem_popsize": 453, "num_cem_iters": 5, "plan_hor": 39}, {"cem_alpha": 0.13363517833108457, "cem_elites_ratio": 0.2328905276720389, "cem_popsize": 376, "num_cem_iters": 6, "plan_hor": 23}, {"cem_alpha": 0.10336074452946224, "cem_elites_ratio": 0.12348662150735154, "cem_popsize": 397, "num_cem_iters": 4, "plan_hor": 26}, {"cem_alpha": 0.1301746578247225, "cem_elites_ratio": 0.24112308608204916, "cem_popsize": 472, "num_cem_iters": 5, "plan_hor": 34}, {"cem_alpha": 0.13979584039482643, "cem_elites_ratio": 0.18133372057888927, "cem_popsize": 358, "num_cem_iters": 6, "plan_hor": 33}, {"cem_alpha": 0.14766639982528956, "cem_elites_ratio": 0.15876456434849026, "cem_popsize": 396, "num_cem_iters": 5, "plan_hor": 37}, {"cem_alpha": 0.14766639982528956, "cem_elites_ratio": 0.18753782034181532, "cem_popsize": 364, "num_cem_iters": 5, "plan_hor": 38}, {"cem_alpha": 0.08672699544121333, "cem_elites_ratio": 0.17845723430342783, "cem_popsize": 345, "num_cem_iters": 5, "plan_hor": 18}, {"cem_alpha": 0.1280863546292353, "cem_elites_ratio": 0.10007766821122334, "cem_popsize": 315, "num_cem_iters": 5, "plan_hor": 24}, {"cem_alpha": 0.12499213251121608, "cem_elites_ratio": 0.07330984466360381, "cem_popsize": 281, "num_cem_iters": 5, "plan_hor": 17}, {"cem_alpha": 0.15466585933875246, "cem_elites_ratio": 0.21185758366547652, "cem_popsize": 407, "num_cem_iters": 6, "plan_hor": 29}, {"cem_alpha": 0.12544326992184393, "cem_elites_ratio": 0.1205702467066725, "cem_popsize": 343, "num_cem_iters": 6, "plan_hor": 31}, {"cem_alpha": 0.14309011772281366, "cem_elites_ratio": 0.21395057298462694, "cem_popsize": 378, "num_cem_iters": 6, "plan_hor": 22}, {"cem_alpha": 0.11254820144018136, "cem_elites_ratio": 0.17980536264850147, "cem_popsize": 512, "num_cem_iters": 6, "plan_hor": 15}, {"cem_alpha": 0.1398920731618436, "cem_elites_ratio": 0.12035362692205663, "cem_popsize": 329, "num_cem_iters": 6, "plan_hor": 10}, {"cem_alpha": 0.14020488045432197, "cem_elites_ratio": 0.12093172018486059, "cem_popsize": 348, "num_cem_iters": 6, "plan_hor": 31}, {"cem_alpha": 0.14816699521063753, "cem_elites_ratio": 0.09818148329319942, "cem_popsize": 411, "num_cem_iters": 5, "plan_hor": 27}, {"cem_alpha": 0.11913036801109973, "cem_elites_ratio": 0.12309551489962596, "cem_popsize": 331, "num_cem_iters": 5, "plan_hor": 29}, {"cem_alpha": 0.12871771706456808, "cem_elites_ratio": 0.17599419645706169, "cem_popsize": 306, "num_cem_iters": 6, "plan_hor": 23}, {"cem_alpha": 0.1364258595320258, "cem_elites_ratio": 0.24264216503423355, "cem_popsize": 345, "num_cem_iters": 5, "plan_hor": 26}, {"cem_alpha": 0.16495783943250975, "cem_elites_ratio": 0.18505039302636872, "cem_popsize": 426, "num_cem_iters": 7, "plan_hor": 27}, {"cem_alpha": 0.14666899515453674, "cem_elites_ratio": 0.16814852465213617, "cem_popsize": 334, "num_cem_iters": 5, "plan_hor": 32}, {"cem_alpha": 0.1602968547338502, "cem_elites_ratio": 0.2430844581374673, "cem_popsize": 394, "num_cem_iters": 5, "plan_hor": 39}, {"cem_alpha": 0.1336600783914425, "cem_elites_ratio": 0.18651520437674518, "cem_popsize": 361, "num_cem_iters": 4, "plan_hor": 29}, {"cem_alpha": 0.1387357228678464, "cem_elites_ratio": 0.16307686760335613, "cem_popsize": 335, "num_cem_iters": 5, "plan_hor": 21}, {"cem_alpha": 0.11692148667409022, "cem_elites_ratio": 0.13721943287293326, "cem_popsize": 400, "num_cem_iters": 4, "plan_hor": 26}, {"cem_alpha": 0.1377208930624623, "cem_elites_ratio": 0.22937446946357468, "cem_popsize": 371, "num_cem_iters": 6, "plan_hor": 38}, {"cem_alpha": 0.13686981585887645, "cem_elites_ratio": 0.11243306301159389, "cem_popsize": 346, "num_cem_iters": 5, "plan_hor": 23}, {"cem_alpha": 0.12125564196905621, "cem_elites_ratio": 0.1465321702191523, "cem_popsize": 358, "num_cem_iters": 5, "plan_hor": 25}, {"cem_alpha": 0.1362311183190184, "cem_elites_ratio": 0.09198186917782858, "cem_popsize": 246, "num_cem_iters": 7, "plan_hor": 7}, {"cem_alpha": 0.1306728046806575, "cem_elites_ratio": 0.1364436381179154, "cem_popsize": 283, "num_cem_iters": 5, "plan_hor": 27}, {"cem_alpha": 0.13481061381046244, "cem_elites_ratio": 0.1476891551756416, "cem_popsize": 387, "num_cem_iters": 5, "plan_hor": 27}, {"cem_alpha": 0.1334953864486037, "cem_elites_ratio": 0.14956424832705148, "cem_popsize": 319, "num_cem_iters": 6, "plan_hor": 40}, {"cem_alpha": 0.14362339359762205, "cem_elites_ratio": 0.10139168565539142, "cem_popsize": 326, "num_cem_iters": 5, "plan_hor": 13}, {"cem_alpha": 0.15098249167188924, "cem_elites_ratio": 0.09455015654189307, "cem_popsize": 331, "num_cem_iters": 6, "plan_hor": 16}, {"cem_alpha": 0.13264907103678616, "cem_elites_ratio": 0.1770430174059866, "cem_popsize": 412, "num_cem_iters": 6, "plan_hor": 27}, {"cem_alpha": 0.14045618720857364, "cem_elites_ratio": 0.22123053860689, "cem_popsize": 352, "num_cem_iters": 5, "plan_hor": 28}, {"cem_alpha": 0.11694108729008808, "cem_elites_ratio": 0.2466965886019071, "cem_popsize": 399, "num_cem_iters": 5, "plan_hor": 22}, {"cem_alpha": 0.13501067403831415, "cem_elites_ratio": 0.09041197253913778, "cem_popsize": 302, "num_cem_iters": 5, "plan_hor": 15}, {"cem_alpha": 0.12361188585737415, "cem_elites_ratio": 0.08410873868373005, "cem_popsize": 303, "num_cem_iters": 4, "plan_hor": 25}, {"cem_alpha": 0.14056723074870883, "cem_elites_ratio": 0.1227122119647938, "cem_popsize": 308, "num_cem_iters": 4, "plan_hor": 36}, {"cem_alpha": 0.12038958740899927, "cem_elites_ratio": 0.2606623888401994, "cem_popsize": 418, "num_cem_iters": 5, "plan_hor": 31}, {"cem_alpha": 0.13627397145581663, "cem_elites_ratio": 0.09467610528363381, "cem_popsize": 267, "num_cem_iters": 5, "plan_hor": 28}, {"cem_alpha": 0.12686270569829533, "cem_elites_ratio": 0.10444679129937733, "cem_popsize": 335, "num_cem_iters": 5, "plan_hor": 12}, {"cem_alpha": 0.12641011961571147, "cem_elites_ratio": 0.12046636582720165, "cem_popsize": 342, "num_cem_iters": 4, "plan_hor": 20}, {"cem_alpha": 0.14183190947075017, "cem_elites_ratio": 0.11655266899414972, "cem_popsize": 322, "num_cem_iters": 4, "plan_hor": 19}, {"cem_alpha": 0.13583247971426188, "cem_elites_ratio": 0.07065539161602298, "cem_popsize": 280, "num_cem_iters": 5, "plan_hor": 32}, {"cem_alpha": 0.11583631313728529, "cem_elites_ratio": 0.07663731185113422, "cem_popsize": 246, "num_cem_iters": 6, "plan_hor": 22}, {"cem_alpha": 0.12397378150191347, "cem_elites_ratio": 0.1372127740056167, "cem_popsize": 334, "num_cem_iters": 5, "plan_hor": 27}, {"cem_alpha": 0.11335314580525706, "cem_elites_ratio": 0.10362465864416998, "cem_popsize": 293, "num_cem_iters": 6, "plan_hor": 16}, {"cem_alpha": 0.11406669328147259, "cem_elites_ratio": 0.10057921807035075, "cem_popsize": 414, "num_cem_iters": 4, "plan_hor": 14}, {"cem_alpha": 0.13616949071120954, "cem_elites_ratio": 0.08026523612636742, "cem_popsize": 344, "num_cem_iters": 6, "plan_hor": 10}, {"cem_alpha": 0.13315807482944328, "cem_elites_ratio": 0.11142145850918764, "cem_popsize": 298, "num_cem_iters": 5, "plan_hor": 17}, {"cem_alpha": 0.1346363501151478, "cem_elites_ratio": 0.10122164446368744, "cem_popsize": 309, "num_cem_iters": 5, "plan_hor": 18}, {"cem_alpha": 0.13821852075636804, "cem_elites_ratio": 0.10191034152273293, "cem_popsize": 301, "num_cem_iters": 5, "plan_hor": 9}, {"cem_alpha": 0.09912590646805633, "cem_elites_ratio": 0.0994767717327148, "cem_popsize": 372, "num_cem_iters": 3, "plan_hor": 28}, {"cem_alpha": 0.13563501906683406, "cem_elites_ratio": 0.1375997642070014, "cem_popsize": 398, "num_cem_iters": 5, "plan_hor": 17}, {"cem_alpha": 0.11330293347934721, "cem_elites_ratio": 0.0689145543587246, "cem_popsize": 302, "num_cem_iters": 5, "plan_hor": 8}, {"cem_alpha": 0.11299262242993477, "cem_elites_ratio": 0.20053231630038673, "cem_popsize": 441, "num_cem_iters": 5, "plan_hor": 22}, {"cem_alpha": 0.11465229611243374, "cem_elites_ratio": 0.08249329048130459, "cem_popsize": 313, "num_cem_iters": 5, "plan_hor": 16}, {"cem_alpha": 0.12099230981598925, "cem_elites_ratio": 0.13171491726469742, "cem_popsize": 346, "num_cem_iters": 4, "plan_hor": 29}, {"cem_alpha": 0.12683932926394054, "cem_elites_ratio": 0.11801945769737254, "cem_popsize": 336, "num_cem_iters": 5, "plan_hor": 28}, {"cem_alpha": 0.13206886370017037, "cem_elites_ratio": 0.16273049602509101, "cem_popsize": 377, "num_cem_iters": 5, "plan_hor": 20}, {"cem_alpha": 0.09801309836610794, "cem_elites_ratio": 0.16591042827718208, "cem_popsize": 362, "num_cem_iters": 4, "plan_hor": 23}, {"cem_alpha": 0.10401658094929314, "cem_elites_ratio": 0.11051309857039378, "cem_popsize": 406, "num_cem_iters": 4, "plan_hor": 11}, {"cem_alpha": 0.09980590756623439, "cem_elites_ratio": 0.12081321327390299, "cem_popsize": 288, "num_cem_iters": 5, "plan_hor": 15}, {"cem_alpha": 0.11609122483832279, "cem_elites_ratio": 0.17659564524532909, "cem_popsize": 322, "num_cem_iters": 5, "plan_hor": 24}, {"cem_alpha": 0.11141973130893097, "cem_elites_ratio": 0.19728741798781277, "cem_popsize": 372, "num_cem_iters": 5, "plan_hor": 22}, {"cem_alpha": 0.09763072819444911, "cem_elites_ratio": 0.1502418932713448, "cem_popsize": 412, "num_cem_iters": 3, "plan_hor": 23}, {"cem_alpha": 0.10840082171325598, "cem_elites_ratio": 0.09233346456768789, "cem_popsize": 350, "num_cem_iters": 4, "plan_hor": 13}, {"cem_alpha": 0.11773126922985919, "cem_elites_ratio": 0.10031419613777612, "cem_popsize": 296, "num_cem_iters": 5, "plan_hor": 22}, {"cem_alpha": 0.1318740000373333, "cem_elites_ratio": 0.1779527227950611, "cem_popsize": 399, "num_cem_iters": 5, "plan_hor": 26}, {"cem_alpha": 0.14232415725860056, "cem_elites_ratio": 0.08263245444857555, "cem_popsize": 274, "num_cem_iters": 4, "plan_hor": 16}, {"cem_alpha": 0.1059191014427292, "cem_elites_ratio": 0.06187378350611065, "cem_popsize": 252, "num_cem_iters": 5, "plan_hor": 12}, {"cem_alpha": 0.11235199037883573, "cem_elites_ratio": 0.12908169338783745, "cem_popsize": 299, "num_cem_iters": 5, "plan_hor": 19}, {"cem_alpha": 0.10096721189166388, "cem_elites_ratio": 0.10436387460995619, "cem_popsize": 348, "num_cem_iters": 4, "plan_hor": 12}, {"cem_alpha": 0.099058917319947, "cem_elites_ratio": 0.08988630155698063, "cem_popsize": 310, "num_cem_iters": 4, "plan_hor": 11}, {"cem_alpha": 0.10167709668911089, "cem_elites_ratio": 0.1130261990096407, "cem_popsize": 300, "num_cem_iters": 4, "plan_hor": 14}, {"cem_alpha": 0.09281171871269409, "cem_elites_ratio": 0.1060829611218611, "cem_popsize": 258, "num_cem_iters": 4, "plan_hor": 18}, {"cem_alpha": 0.11612321970176769, "cem_elites_ratio": 0.1448885943683364, "cem_popsize": 373, "num_cem_iters": 4, "plan_hor": 21}, {"cem_alpha": 0.12912432127357895, "cem_elites_ratio": 0.07859087219897978, "cem_popsize": 280, "num_cem_iters": 5, "plan_hor": 12}, {"cem_alpha": 0.09279287556760568, "cem_elites_ratio": 0.09166673812853905, "cem_popsize": 337, "num_cem_iters": 4, "plan_hor": 10}, {"cem_alpha": 0.08571550596198632, "cem_elites_ratio": 0.09247456611393184, "cem_popsize": 429, "num_cem_iters": 3, "plan_hor": 13}, {"cem_alpha": 0.08494439497205884, "cem_elites_ratio": 0.09349917499457021, "cem_popsize": 356, "num_cem_iters": 4, "plan_hor": 12}, {"cem_alpha": 0.09604215606784208, "cem_elites_ratio": 0.09091075735032543, "cem_popsize": 323, "num_cem_iters": 5, "plan_hor": 16}, {"cem_alpha": 0.09388000038600004, "cem_elites_ratio": 0.12696481962655942, "cem_popsize": 327, "num_cem_iters": 4, "plan_hor": 22}, {"cem_alpha": 0.09163854064374793, "cem_elites_ratio": 0.1189302120595241, "cem_popsize": 326, "num_cem_iters": 4, "plan_hor": 22}, {"cem_alpha": 0.11069273499780422, "cem_elites_ratio": 0.13963010522689168, "cem_popsize": 345, "num_cem_iters": 4, "plan_hor": 20}, {"cem_alpha": 0.11226877302729399, "cem_elites_ratio": 0.16843245402367454, "cem_popsize": 440, "num_cem_iters": 5, "plan_hor": 20}, {"cem_alpha": 0.08907927215860499, "cem_elites_ratio": 0.07520350176557009, "cem_popsize": 334, "num_cem_iters": 5, "plan_hor": 23}, {"cem_alpha": 0.09089122809394581, "cem_elites_ratio": 0.09299495758313175, "cem_popsize": 382, "num_cem_iters": 4, "plan_hor": 25}, {"cem_alpha": 0.09141116069538094, "cem_elites_ratio": 0.10408039888697279, "cem_popsize": 366, "num_cem_iters": 4, "plan_hor": 27}, {"cem_alpha": 0.0957387260506834, "cem_elites_ratio": 0.07190209383672995, "cem_popsize": 333, "num_cem_iters": 4, "plan_hor": 24}, {"cem_alpha": 0.08724393373304593, "cem_elites_ratio": 0.08129680123007865, "cem_popsize": 304, "num_cem_iters": 4, "plan_hor": 28}, {"cem_alpha": 0.0860323510028905, "cem_elites_ratio": 0.08292519335019959, "cem_popsize": 318, "num_cem_iters": 4, "plan_hor": 26}, {"cem_alpha": 0.10452550228453125, "cem_elites_ratio": 0.09024725581459822, "cem_popsize": 398, "num_cem_iters": 5, "plan_hor": 21}, {"cem_alpha": 0.11388081059053708, "cem_elites_ratio": 0.07609423689844538, "cem_popsize": 317, "num_cem_iters": 4, "plan_hor": 12}, {"cem_alpha": 0.08147720411750027, "cem_elites_ratio": 0.1510341863848056, "cem_popsize": 317, "num_cem_iters": 4, "plan_hor": 30}, {"cem_alpha": 0.10129833710895342, "cem_elites_ratio": 0.08097223863524838, "cem_popsize": 314, "num_cem_iters": 4, "plan_hor": 24}, {"cem_alpha": 0.1060490526637838, "cem_elites_ratio": 0.1120924082672416, "cem_popsize": 382, "num_cem_iters": 5, "plan_hor": 34}, {"cem_alpha": 0.12392893773873481, "cem_elites_ratio": 0.14267371076690807, "cem_popsize": 543, "num_cem_iters": 4, "plan_hor": 43}, {"cem_alpha": 0.11464228125976542, "cem_elites_ratio": 0.1063941735330667, "cem_popsize": 424, "num_cem_iters": 4, "plan_hor": 42}, {"cem_alpha": 0.09217558329783963, "cem_elites_ratio": 0.18542043291640606, "cem_popsize": 389, "num_cem_iters": 4, "plan_hor": 42}, {"cem_alpha": 0.09182207831555232, "cem_elites_ratio": 0.11671949293618582, "cem_popsize": 417, "num_cem_iters": 5, "plan_hor": 33}, {"cem_alpha": 0.10512101357983912, "cem_elites_ratio": 0.06988080623788319, "cem_popsize": 366, "num_cem_iters": 5, "plan_hor": 25}, {"cem_alpha": 0.10710347891211425, "cem_elites_ratio": 0.04924535611975775, "cem_popsize": 328, "num_cem_iters": 5, "plan_hor": 27}, {"cem_alpha": 0.10535652319951501, "cem_elites_ratio": 0.06113370401246687, "cem_popsize": 257, "num_cem_iters": 4, "plan_hor": 16}, {"cem_alpha": 0.10177735928865388, "cem_elites_ratio": 0.09662583099949747, "cem_popsize": 338, "num_cem_iters": 4, "plan_hor": 22}, {"cem_alpha": 0.12312741147151576, "cem_elites_ratio": 0.09158609524231334, "cem_popsize": 313, "num_cem_iters": 5, "plan_hor": 21}, {"cem_alpha": 0.10791220934577976, "cem_elites_ratio": 0.0458963664499432, "cem_popsize": 280, "num_cem_iters": 4, "plan_hor": 27}, {"cem_alpha": 0.09612692194633672, "cem_elites_ratio": 0.06985073956481064, "cem_popsize": 292, "num_cem_iters": 4, "plan_hor": 32}, {"cem_alpha": 0.08890287162335123, "cem_elites_ratio": 0.0578393463546935, "cem_popsize": 262, "num_cem_iters": 4, "plan_hor": 22}, {"cem_alpha": 0.1044244602507739, "cem_elites_ratio": 0.10383455242160489, "cem_popsize": 360, "num_cem_iters": 5, "plan_hor": 33}, {"cem_alpha": 0.1052311011874137, "cem_elites_ratio": 0.10553831740865553, "cem_popsize": 362, "num_cem_iters": 4, "plan_hor": 40}, {"cem_alpha": 0.09225313855587998, "cem_elites_ratio": 0.1073173846495763, "cem_popsize": 343, "num_cem_iters": 4, "plan_hor": 39}, {"cem_alpha": 0.12284183011787839, "cem_elites_ratio": 0.08129639836030786, "cem_popsize": 303, "num_cem_iters": 5, "plan_hor": 24}, {"cem_alpha": 0.10526046023643329, "cem_elites_ratio": 0.19964167825228932, "cem_popsize": 334, "num_cem_iters": 5, "plan_hor": 25}, {"cem_alpha": 0.13174699230172404, "cem_elites_ratio": 0.10842984925078424, "cem_popsize": 350, "num_cem_iters": 5, "plan_hor": 34}, {"cem_alpha": 0.09668803354045988, "cem_elites_ratio": 0.06435619815057146, "cem_popsize": 319, "num_cem_iters": 4, "plan_hor": 33}, {"cem_alpha": 0.08796186102449152, "cem_elites_ratio": 0.09850242102107983, "cem_popsize": 364, "num_cem_iters": 4, "plan_hor": 39}, {"cem_alpha": 0.10097656750810471, "cem_elites_ratio": 0.16246363442893183, "cem_popsize": 412, "num_cem_iters": 4, "plan_hor": 37}, {"cem_alpha": 0.11276459847129135, "cem_elites_ratio": 0.046570815460754894, "cem_popsize": 286, "num_cem_iters": 4, "plan_hor": 26}, {"cem_alpha": 0.14449537264405266, "cem_elites_ratio": 0.17696678276635344, "cem_popsize": 384, "num_cem_iters": 5, "plan_hor": 32}, {"cem_alpha": 0.11822423599366812, "cem_elites_ratio": 0.07262899670606711, "cem_popsize": 305, "num_cem_iters": 4, "plan_hor": 21}, {"cem_alpha": 0.11839643042914094, "cem_elites_ratio": 0.07646791719395514, "cem_popsize": 273, "num_cem_iters": 5, "plan_hor": 16}, {"cem_alpha": 0.14712890401496087, "cem_elites_ratio": 0.19966293791728837, "cem_popsize": 420, "num_cem_iters": 5, "plan_hor": 32}, {"cem_alpha": 0.1323142887961533, "cem_elites_ratio": 0.08215823753682285, "cem_popsize": 391, "num_cem_iters": 4, "plan_hor": 32}, {"cem_alpha": 0.16808564568411227, "cem_elites_ratio": 0.13367008282279788, "cem_popsize": 325, "num_cem_iters": 5, "plan_hor": 35}, {"cem_alpha": 0.14867557591418, "cem_elites_ratio": 0.08083584207512369, "cem_popsize": 304, "num_cem_iters": 5, "plan_hor": 30}, {"cem_alpha": 0.10849989300494225, "cem_elites_ratio": 0.10401183902281647, "cem_popsize": 317, "num_cem_iters": 4, "plan_hor": 23}, {"cem_alpha": 0.12045625002691915, "cem_elites_ratio": 0.11482579947794518, "cem_popsize": 317, "num_cem_iters": 4, "plan_hor": 27}, {"cem_alpha": 0.133165306940388, "cem_elites_ratio": 0.056290393556807344, "cem_popsize": 329, "num_cem_iters": 4, "plan_hor": 30}, {"cem_alpha": 0.1137139789523697, "cem_elites_ratio": 0.04519504175357324, "cem_popsize": 298, "num_cem_iters": 4, "plan_hor": 27}, {"cem_alpha": 0.14292492141244026, "cem_elites_ratio": 0.12563441726014166, "cem_popsize": 312, "num_cem_iters": 4, "plan_hor": 23}, {"cem_alpha": 0.09814550245459118, "cem_elites_ratio": 0.11516356178324795, "cem_popsize": 373, "num_cem_iters": 5, "plan_hor": 23}, {"cem_alpha": 0.11520755383851226, "cem_elites_ratio": 0.08385492031746258, "cem_popsize": 440, "num_cem_iters": 5, "plan_hor": 33}, {"cem_alpha": 0.11178589407040056, "cem_elites_ratio": 0.0842817737350431, "cem_popsize": 353, "num_cem_iters": 5, "plan_hor": 30}, {"cem_alpha": 0.09485463582418727, "cem_elites_ratio": 0.1326242525646686, "cem_popsize": 289, "num_cem_iters": 5, "plan_hor": 26}, {"cem_alpha": 0.11010420088260822, "cem_elites_ratio": 0.07498117227126241, "cem_popsize": 406, "num_cem_iters": 5, "plan_hor": 28}, {"cem_alpha": 0.10326290164019089, "cem_elites_ratio": 0.061352675076512826, "cem_popsize": 394, "num_cem_iters": 6, "plan_hor": 28}, {"cem_alpha": 0.10178608755851346, "cem_elites_ratio": 0.060956175209290676, "cem_popsize": 391, "num_cem_iters": 6, "plan_hor": 28}, {"cem_alpha": 0.09235734588093183, "cem_elites_ratio": 0.06815356357298182, "cem_popsize": 476, "num_cem_iters": 6, "plan_hor": 30}, {"cem_alpha": 0.1384592392560565, "cem_elites_ratio": 0.08790619176027797, "cem_popsize": 312, "num_cem_iters": 5, "plan_hor": 30}, {"cem_alpha": 0.14372433357205808, "cem_elites_ratio": 0.12284048193018264, "cem_popsize": 334, "num_cem_iters": 4, "plan_hor": 24}, {"cem_alpha": 0.1213778070503774, "cem_elites_ratio": 0.06478079420817023, "cem_popsize": 368, "num_cem_iters": 5, "plan_hor": 28}, {"cem_alpha": 0.1367810104496457, "cem_elites_ratio": 0.08737207523610589, "cem_popsize": 318, "num_cem_iters": 5, "plan_hor": 30}, {"cem_alpha": 0.12679976590212136, "cem_elites_ratio": 0.08054768585081072, "cem_popsize": 354, "num_cem_iters": 5, "plan_hor": 25}, {"cem_alpha": 0.1333072281843996, "cem_elites_ratio": 0.07036355982875654, "cem_popsize": 307, "num_cem_iters": 5, "plan_hor": 33}, {"cem_alpha": 0.14792827920354606, "cem_elites_ratio": 0.09546674262093105, "cem_popsize": 335, "num_cem_iters": 4, "plan_hor": 29}, {"cem_alpha": 0.1119188681927918, "cem_elites_ratio": 0.17887944145599818, "cem_popsize": 418, "num_cem_iters": 4, "plan_hor": 39}, {"cem_alpha": 0.10599237612992071, "cem_elites_ratio": 0.09667904456764725, "cem_popsize": 403, "num_cem_iters": 4, "plan_hor": 28}, {"cem_alpha": 0.11658922437176193, "cem_elites_ratio": 0.09596748044153869, "cem_popsize": 348, "num_cem_iters": 4, "plan_hor": 30}, {"cem_alpha": 0.13342351601582964, "cem_elites_ratio": 0.09609598727820892, "cem_popsize": 316, "num_cem_iters": 4, "plan_hor": 26}, {"cem_alpha": 0.08669079493314628, "cem_elites_ratio": 0.07981355850729249, "cem_popsize": 389, "num_cem_iters": 5, "plan_hor": 32}, {"cem_alpha": 0.12334201780125284, "cem_elites_ratio": 0.08413845996764929, "cem_popsize": 379, "num_cem_iters": 5, "plan_hor": 30}, {"cem_alpha": 0.13003916223029516, "cem_elites_ratio": 0.15534623552348306, "cem_popsize": 355, "num_cem_iters": 4, "plan_hor": 27}, {"cem_alpha": 0.18426146181084418, "cem_elites_ratio": 0.1300024729876033, "cem_popsize": 393, "num_cem_iters": 5, "plan_hor": 39}, {"cem_alpha": 0.13142201736641762, "cem_elites_ratio": 0.07506740729914227, "cem_popsize": 391, "num_cem_iters": 5, "plan_hor": 35}, {"cem_alpha": 0.1326167759957649, "cem_elites_ratio": 0.059050589307440025, "cem_popsize": 315, "num_cem_iters": 4, "plan_hor": 29}, {"cem_alpha": 0.11769886374971113, "cem_elites_ratio": 0.07204220416540705, "cem_popsize": 356, "num_cem_iters": 5, "plan_hor": 29}, {"cem_alpha": 0.15789309726628598, "cem_elites_ratio": 0.16268005613186937, "cem_popsize": 299, "num_cem_iters": 4, "plan_hor": 26}, {"cem_alpha": 0.14574478495931556, "cem_elites_ratio": 0.1527682077847802, "cem_popsize": 324, "num_cem_iters": 4, "plan_hor": 38}, {"cem_alpha": 0.1333698931574281, "cem_elites_ratio": 0.07111589317463073, "cem_popsize": 457, "num_cem_iters": 5, "plan_hor": 32}, {"cem_alpha": 0.16270039942042958, "cem_elites_ratio": 0.11393223229503924, "cem_popsize": 371, "num_cem_iters": 5, "plan_hor": 37}, {"cem_alpha": 0.1466677475500655, "cem_elites_ratio": 0.09055581003447966, "cem_popsize": 386, "num_cem_iters": 5, "plan_hor": 36}, {"cem_alpha": 0.1342306687673373, "cem_elites_ratio": 0.0823145794380934, "cem_popsize": 323, "num_cem_iters": 4, "plan_hor": 29}, {"cem_alpha": 0.12493977288071079, "cem_elites_ratio": 0.10480029385881515, "cem_popsize": 312, "num_cem_iters": 5, "plan_hor": 32}, {"cem_alpha": 0.11465472350156339, "cem_elites_ratio": 0.11036948265520642, "cem_popsize": 429, "num_cem_iters": 5, "plan_hor": 30}, {"cem_alpha": 0.14482495508719379, "cem_elites_ratio": 0.06338302517479967, "cem_popsize": 420, "num_cem_iters": 4, "plan_hor": 34}, {"cem_alpha": 0.10376923789676602, "cem_elites_ratio": 0.06028799734747794, "cem_popsize": 393, "num_cem_iters": 6, "plan_hor": 27}, {"cem_alpha": 0.12155060075793656, "cem_elites_ratio": 0.19649260549492456, "cem_popsize": 386, "num_cem_iters": 4, "plan_hor": 29}, {"cem_alpha": 0.13763116166056721, "cem_elites_ratio": 0.08830818490411281, "cem_popsize": 325, "num_cem_iters": 4, "plan_hor": 27}, {"cem_alpha": 0.11700849001536082, "cem_elites_ratio": 0.08292682746019, "cem_popsize": 338, "num_cem_iters": 4, "plan_hor": 30}, {"cem_alpha": 0.1185795734015884, "cem_elites_ratio": 0.06278119452721836, "cem_popsize": 394, "num_cem_iters": 6, "plan_hor": 29}, {"cem_alpha": 0.14593999607788968, "cem_elites_ratio": 0.07342540001741249, "cem_popsize": 376, "num_cem_iters": 4, "plan_hor": 31}, {"cem_alpha": 0.13601186473130628, "cem_elites_ratio": 0.07056868259405051, "cem_popsize": 372, "num_cem_iters": 5, "plan_hor": 28}, {"cem_alpha": 0.11441870373803213, "cem_elites_ratio": 0.17379999763563675, "cem_popsize": 389, "num_cem_iters": 4, "plan_hor": 28}, {"cem_alpha": 0.14763374672043295, "cem_elites_ratio": 0.0842461211319904, "cem_popsize": 321, "num_cem_iters": 4, "plan_hor": 27}, {"cem_alpha": 0.1400899228779935, "cem_elites_ratio": 0.12527857525468367, "cem_popsize": 354, "num_cem_iters": 4, "plan_hor": 30}, {"cem_alpha": 0.16005102964113085, "cem_elites_ratio": 0.08473316987110008, "cem_popsize": 297, "num_cem_iters": 4, "plan_hor": 30}, {"cem_alpha": 0.1771141382856364, "cem_elites_ratio": 0.10509948949446293, "cem_popsize": 327, "num_cem_iters": 4, "plan_hor": 32}, {"cem_alpha": 0.09946537971587747, "cem_elites_ratio": 0.06075888722573092, "cem_popsize": 415, "num_cem_iters": 6, "plan_hor": 27}, {"cem_alpha": 0.12703274846023654, "cem_elites_ratio": 0.07306082269957422, "cem_popsize": 329, "num_cem_iters": 4, "plan_hor": 34}, {"cem_alpha": 0.1380956485590733, "cem_elites_ratio": 0.12151419398677765, "cem_popsize": 392, "num_cem_iters": 4, "plan_hor": 33}, {"cem_alpha": 0.10962928923824185, "cem_elites_ratio": 0.1926088209882441, "cem_popsize": 377, "num_cem_iters": 4, "plan_hor": 21}, {"cem_alpha": 0.13524229126257406, "cem_elites_ratio": 0.17302487161892677, "cem_popsize": 394, "num_cem_iters": 4, "plan_hor": 25}, {"cem_alpha": 0.1597509370253776, "cem_elites_ratio": 0.12019565800995302, "cem_popsize": 360, "num_cem_iters": 4, "plan_hor": 34}, {"cem_alpha": 0.10790306843581621, "cem_elites_ratio": 0.2411077535969884, "cem_popsize": 352, "num_cem_iters": 4, "plan_hor": 28}, {"cem_alpha": 0.13725420958850343, "cem_elites_ratio": 0.107685527360696, "cem_popsize": 439, "num_cem_iters": 5, "plan_hor": 28}, {"cem_alpha": 0.11092554647025014, "cem_elites_ratio": 0.11646859847793277, "cem_popsize": 425, "num_cem_iters": 5, "plan_hor": 30}, {"cem_alpha": 0.14149443881576587, "cem_elites_ratio": 0.10311355761401007, "cem_popsize": 345, "num_cem_iters": 5, "plan_hor": 30}, {"cem_alpha": 0.14435852752026662, "cem_elites_ratio": 0.13021364665597132, "cem_popsize": 409, "num_cem_iters": 4, "plan_hor": 24}, {"cem_alpha": 0.14174354165358088, "cem_elites_ratio": 0.12009120734459859, "cem_popsize": 343, "num_cem_iters": 4, "plan_hor": 30}, {"cem_alpha": 0.1358144806139118, "cem_elites_ratio": 0.08846531044005086, "cem_popsize": 351, "num_cem_iters": 4, "plan_hor": 32}, {"cem_alpha": 0.16421878888230396, "cem_elites_ratio": 0.16733138356885996, "cem_popsize": 402, "num_cem_iters": 4, "plan_hor": 30}, {"cem_alpha": 0.14550664315716216, "cem_elites_ratio": 0.10653054479671346, "cem_popsize": 367, "num_cem_iters": 4, "plan_hor": 29}, {"cem_alpha": 0.12444445509662998, "cem_elites_ratio": 0.19150465790859866, "cem_popsize": 381, "num_cem_iters": 4, "plan_hor": 25}, {"cem_alpha": 0.1736910575503385, "cem_elites_ratio": 0.16827481919394163, "cem_popsize": 376, "num_cem_iters": 4, "plan_hor": 34}, {"cem_alpha": 0.16011421174707904, "cem_elites_ratio": 0.286219673384183, "cem_popsize": 371, "num_cem_iters": 4, "plan_hor": 25}, {"cem_alpha": 0.13507989473335333, "cem_elites_ratio": 0.09959924638764935, "cem_popsize": 362, "num_cem_iters": 4, "plan_hor": 30}, {"cem_alpha": 0.1358669523891758, "cem_elites_ratio": 0.13254056050629281, "cem_popsize": 409, "num_cem_iters": 4, "plan_hor": 29}, {"cem_alpha": 0.15135888390813096, "cem_elites_ratio": 0.13673977381429908, "cem_popsize": 310, "num_cem_iters": 5, "plan_hor": 29}, {"cem_alpha": 0.13650482205239223, "cem_elites_ratio": 0.13159310235846758, "cem_popsize": 383, "num_cem_iters": 4, "plan_hor": 31}, {"cem_alpha": 0.12705603932065418, "cem_elites_ratio": 0.10193573014920074, "cem_popsize": 373, "num_cem_iters": 4, "plan_hor": 29}, {"cem_alpha": 0.14726679901812703, "cem_elites_ratio": 0.17094488089973967, "cem_popsize": 436, "num_cem_iters": 4, "plan_hor": 32}, {"cem_alpha": 0.15950417216650475, "cem_elites_ratio": 0.13028456010351874, "cem_popsize": 450, "num_cem_iters": 4, "plan_hor": 30}, {"cem_alpha": 0.15953602487214127, "cem_elites_ratio": 0.156359005907634, "cem_popsize": 497, "num_cem_iters": 4, "plan_hor": 31}, {"cem_alpha": 0.13113778581413696, "cem_elites_ratio": 0.16828221917634636, "cem_popsize": 467, "num_cem_iters": 4, "plan_hor": 32}, {"cem_alpha": 0.14443694326338935, "cem_elites_ratio": 0.1864168034415072, "cem_popsize": 405, "num_cem_iters": 4, "plan_hor": 23}, {"cem_alpha": 0.15688138489868547, "cem_elites_ratio": 0.1493404818371672, "cem_popsize": 481, "num_cem_iters": 4, "plan_hor": 34}, {"cem_alpha": 0.18207107486066398, "cem_elites_ratio": 0.20474759760162525, "cem_popsize": 465, "num_cem_iters": 4, "plan_hor": 30}, {"cem_alpha": 0.17497157418116888, "cem_elites_ratio": 0.2085346667144251, "cem_popsize": 590, "num_cem_iters": 4, "plan_hor": 29}, {"cem_alpha": 0.160516114247099, "cem_elites_ratio": 0.15413606544817363, "cem_popsize": 514, "num_cem_iters": 4, "plan_hor": 28}, {"cem_alpha": 0.14627822698939086, "cem_elites_ratio": 0.14294754247188746, "cem_popsize": 483, "num_cem_iters": 4, "plan_hor": 32}, {"cem_alpha": 0.14252710220793835, "cem_elites_ratio": 0.19982590010310083, "cem_popsize": 361, "num_cem_iters": 5, "plan_hor": 30}, {"cem_alpha": 0.16047053685642623, "cem_elites_ratio": 0.16360613124692686, "cem_popsize": 469, "num_cem_iters": 4, "plan_hor": 29}, {"cem_alpha": 0.15819262858946562, "cem_elites_ratio": 0.2188660848826215, "cem_popsize": 450, "num_cem_iters": 3, "plan_hor": 28}, {"cem_alpha": 0.16710539780487077, "cem_elites_ratio": 0.1364253264591892, "cem_popsize": 432, "num_cem_iters": 4, "plan_hor": 34}, {"cem_alpha": 0.16402934359919177, "cem_elites_ratio": 0.12827344060947712, "cem_popsize": 429, "num_cem_iters": 4, "plan_hor": 30}, {"cem_alpha": 0.1570499392960532, "cem_elites_ratio": 0.11304191913702916, "cem_popsize": 490, "num_cem_iters": 4, "plan_hor": 29}, {"cem_alpha": 0.13967644110073468, "cem_elites_ratio": 0.15613064109410327, "cem_popsize": 360, "num_cem_iters": 4, "plan_hor": 31}, {"cem_alpha": 0.16896344368197572, "cem_elites_ratio": 0.20857045182489065, "cem_popsize": 498, "num_cem_iters": 3, "plan_hor": 31}, {"cem_alpha": 0.16245534311191795, "cem_elites_ratio": 0.15091946724231456, "cem_popsize": 448, "num_cem_iters": 4, "plan_hor": 23}, {"cem_alpha": 0.16284319568028427, "cem_elites_ratio": 0.15660941362575959, "cem_popsize": 411, "num_cem_iters": 5, "plan_hor": 32}, {"cem_alpha": 0.151394116184864, "cem_elites_ratio": 0.12320847723755027, "cem_popsize": 430, "num_cem_iters": 4, "plan_hor": 31}, {"cem_alpha": 0.1492416470010865, "cem_elites_ratio": 0.1514268747598907, "cem_popsize": 445, "num_cem_iters": 4, "plan_hor": 30}, {"cem_alpha": 0.1425372693864406, "cem_elites_ratio": 0.21993403073180415, "cem_popsize": 482, "num_cem_iters": 6, "plan_hor": 28}, {"cem_alpha": 0.16177914573111218, "cem_elites_ratio": 0.1340474872959858, "cem_popsize": 528, "num_cem_iters": 4, "plan_hor": 34}, {"cem_alpha": 0.14119038050866373, "cem_elites_ratio": 0.20061293584087392, "cem_popsize": 480, "num_cem_iters": 4, "plan_hor": 26}, {"cem_alpha": 0.14755204700108646, "cem_elites_ratio": 0.17393961335035035, "cem_popsize": 445, "num_cem_iters": 4, "plan_hor": 31}, {"cem_alpha": 0.17614297848430743, "cem_elites_ratio": 0.18543306293775824, "cem_popsize": 584, "num_cem_iters": 4, "plan_hor": 30}, {"cem_alpha": 0.1766515741811689, "cem_elites_ratio": 0.2219749692908471, "cem_popsize": 556, "num_cem_iters": 4, "plan_hor": 34}, {"cem_alpha": 0.14178784068444938, "cem_elites_ratio": 0.16833633990232183, "cem_popsize": 522, "num_cem_iters": 5, "plan_hor": 30}, {"cem_alpha": 0.17149972692585963, "cem_elites_ratio": 0.1415869888313712, "cem_popsize": 535, "num_cem_iters": 5, "plan_hor": 27}, {"cem_alpha": 0.16586575508063717, "cem_elites_ratio": 0.17897114504107026, "cem_popsize": 518, "num_cem_iters": 4, "plan_hor": 27}, {"cem_alpha": 0.18899203689338792, "cem_elites_ratio": 0.23353396158244943, "cem_popsize": 553, "num_cem_iters": 4, "plan_hor": 29}, {"cem_alpha": 0.14976044782320302, "cem_elites_ratio": 0.2304838803911406, "cem_popsize": 562, "num_cem_iters": 4, "plan_hor": 26}, {"cem_alpha": 0.16613723608913095, "cem_elites_ratio": 0.2619790612817909, "cem_popsize": 593, "num_cem_iters": 3, "plan_hor": 30}, {"cem_alpha": 0.15760551929258254, "cem_elites_ratio": 0.2446406427184695, "cem_popsize": 542, "num_cem_iters": 3, "plan_hor": 27}, {"cem_alpha": 0.1494439844069055, "cem_elites_ratio": 0.07823949034567312, "cem_popsize": 532, "num_cem_iters": 5, "plan_hor": 27}, {"cem_alpha": 0.1564897637386281, "cem_elites_ratio": 0.24104594198339163, "cem_popsize": 593, "num_cem_iters": 5, "plan_hor": 28}, {"cem_alpha": 0.14927905377109982, "cem_elites_ratio": 0.14361756652298008, "cem_popsize": 600, "num_cem_iters": 5, "plan_hor": 27}, {"cem_alpha": 0.16307969863433905, "cem_elites_ratio": 0.21863616149917003, "cem_popsize": 530, "num_cem_iters": 4, "plan_hor": 34}, {"cem_alpha": 0.18444800000000003, "cem_elites_ratio": 0.20616238329515324, "cem_popsize": 600, "num_cem_iters": 4, "plan_hor": 27}, {"cem_alpha": 0.13083104978338814, "cem_elites_ratio": 0.13941993660924967, "cem_popsize": 482, "num_cem_iters": 5, "plan_hor": 30}, {"cem_alpha": 0.14155246890236164, "cem_elites_ratio": 0.19840080006264782, "cem_popsize": 555, "num_cem_iters": 5, "plan_hor": 27}, {"cem_alpha": 0.10091938359359531, "cem_elites_ratio": 0.2424648497509688, "cem_popsize": 572, "num_cem_iters": 6, "plan_hor": 29}, {"cem_alpha": 0.17021654234845643, "cem_elites_ratio": 0.17401135242561225, "cem_popsize": 508, "num_cem_iters": 5, "plan_hor": 29}, {"cem_alpha": 0.08764562926672854, "cem_elites_ratio": 0.14875521440095293, "cem_popsize": 600, "num_cem_iters": 6, "plan_hor": 29}, {"cem_alpha": 0.09431781613736309, "cem_elites_ratio": 0.13540105141450487, "cem_popsize": 551, "num_cem_iters": 6, "plan_hor": 28}, {"cem_alpha": 0.14593451116976813, "cem_elites_ratio": 0.1567473986332286, "cem_popsize": 563, "num_cem_iters": 4, "plan_hor": 30}, {"cem_alpha": 0.13069658888254979, "cem_elites_ratio": 0.10870165862442582, "cem_popsize": 572, "num_cem_iters": 7, "plan_hor": 26}, {"cem_alpha": 0.12949379043845305, "cem_elites_ratio": 0.14600611615044765, "cem_popsize": 522, "num_cem_iters": 5, "plan_hor": 31}, {"cem_alpha": 0.13022782915075454, "cem_elites_ratio": 0.1427135148199156, "cem_popsize": 649, "num_cem_iters": 6, "plan_hor": 30}, {"cem_alpha": 0.15312686117664706, "cem_elites_ratio": 0.16540081763027964, "cem_popsize": 609, "num_cem_iters": 4, "plan_hor": 30}, {"cem_alpha": 0.188833664, "cem_elites_ratio": 0.27301120283278796, "cem_popsize": 631, "num_cem_iters": 4, "plan_hor": 24}, {"cem_alpha": 0.16602896823353627, "cem_elites_ratio": 0.1223813393179187, "cem_popsize": 524, "num_cem_iters": 6, "plan_hor": 27}, {"cem_alpha": 0.1388249021439421, "cem_elites_ratio": 0.1606580971404753, "cem_popsize": 545, "num_cem_iters": 5, "plan_hor": 32}, {"cem_alpha": 0.1459769021439421, "cem_elites_ratio": 0.14313296502361347, "cem_popsize": 613, "num_cem_iters": 5, "plan_hor": 30}, {"cem_alpha": 0.1754339451114137, "cem_elites_ratio": 0.2254990189422489, "cem_popsize": 612, "num_cem_iters": 3, "plan_hor": 27}, {"cem_alpha": 0.14789932162078195, "cem_elites_ratio": 0.12603096562147, "cem_popsize": 528, "num_cem_iters": 4, "plan_hor": 29}, {"cem_alpha": 0.13028828457511493, "cem_elites_ratio": 0.11435185247334323, "cem_popsize": 625, "num_cem_iters": 6, "plan_hor": 31}, {"cem_alpha": 0.1541245520259774, "cem_elites_ratio": 0.1694931620630635, "cem_popsize": 599, "num_cem_iters": 4, "plan_hor": 35}, {"cem_alpha": 0.1327410418829353, "cem_elites_ratio": 0.21471989754586077, "cem_popsize": 630, "num_cem_iters": 6, "plan_hor": 31}, {"cem_alpha": 0.15088229176497062, "cem_elites_ratio": 0.19946209398719603, "cem_popsize": 565, "num_cem_iters": 5, "plan_hor": 32}, {"cem_alpha": 0.15965932162078195, "cem_elites_ratio": 0.11356601153750673, "cem_popsize": 555, "num_cem_iters": 4, "plan_hor": 27}, {"cem_alpha": 0.14944915011796472, "cem_elites_ratio": 0.17426416262750322, "cem_popsize": 509, "num_cem_iters": 4, "plan_hor": 31}, {"cem_alpha": 0.16223655202597742, "cem_elites_ratio": 0.1189751304412611, "cem_popsize": 509, "num_cem_iters": 4, "plan_hor": 27}, {"cem_alpha": 0.12300069458862353, "cem_elites_ratio": 0.16397499596508755, "cem_popsize": 597, "num_cem_iters": 5, "plan_hor": 30}, {"cem_alpha": 0.1398107501179647, "cem_elites_ratio": 0.20855576523942881, "cem_popsize": 627, "num_cem_iters": 5, "plan_hor": 26}, {"cem_alpha": 0.15088229176497062, "cem_elites_ratio": 0.20331671727530645, "cem_popsize": 565, "num_cem_iters": 4, "plan_hor": 30}, {"cem_alpha": 0.15465326117664707, "cem_elites_ratio": 0.19491031793835242, "cem_popsize": 683, "num_cem_iters": 4, "plan_hor": 31}, {"cem_alpha": 0.17652464475108537, "cem_elites_ratio": 0.2073603988831613, "cem_popsize": 492, "num_cem_iters": 4, "plan_hor": 35}, {"cem_alpha": 0.14625178279742898, "cem_elites_ratio": 0.17139281487427904, "cem_popsize": 617, "num_cem_iters": 5, "plan_hor": 27}, {"cem_alpha": 0.12068709458862355, "cem_elites_ratio": 0.19108340884743927, "cem_popsize": 527, "num_cem_iters": 5, "plan_hor": 26}, {"cem_alpha": 0.11091240484086884, "cem_elites_ratio": 0.2331009950051014, "cem_popsize": 558, "num_cem_iters": 5, "plan_hor": 34}]